LICENSE
MANIFEST.in
README.md
setup.py
Rawstonpact.egg-info/PKG-INFO
Rawstonpact.egg-info/SOURCES.txt
Rawstonpact.egg-info/dependency_links.txt
Rawstonpact.egg-info/not-zip-safe
Rawstonpact.egg-info/requires.txt
Rawstonpact.egg-info/top_level.txt
libpythonpro/__init__.py
libpythonpro/github_api.py